repo_structure/__init__.py
repo_structure/__main__.py
repo_structure/__main___test.py
repo_structure/_version.py
repo_structure/config.schema.json
repo_structure/repo_structure_benchmark_test.py
repo_structure/repo_structure_config.py
repo_structure/repo_structure_config_test.py
repo_structure/repo_structure_diff_scan.py
repo_structure/repo_structure_diff_scan_test.py
repo_structure/repo_structure_full_scan.py
repo_structure/repo_structure_full_scan_test.py
repo_structure/repo_structure_lib.py
repo_structure/repo_structure_lib_test.py
repo_structure/repo_structure_report.py
repo_structure/repo_structure_report_test.py
repo_structure/repo_structure_schema.py
repo_structure/repo_structure_test_lib.py
repo_structure/test_config_allow_all.yaml
repo_structure/test_config_bad_config.yaml
repo_structure/test_config_fail.yaml
repo_structure/test_config_with_warnings.yaml
repo_structure-0.10.1.dist-info/licenses/LICENSE
repo_structure-0.10.1.dist-info/METADATA
repo_structure-0.10.1.dist-info/WHEEL
repo_structure-0.10.1.dist-info/entry_points.txt
repo_structure-0.10.1.dist-info/top_level.txt
repo_structure-0.10.1.dist-info/RECORD
