Metadata-Version: 2.4
Name: repo-structure
Version: 0.10.1
Summary: Check the directory structure of your repository
Author-email: Jochen Issing <c.333+git@nesono.com>
License-Expression: BSD-3-Clause
Classifier: Programming Language :: Python :: 3
Classifier: Programming Language :: Python :: 3.10
Classifier: Programming Language :: Python :: 3.11
Classifier: Programming Language :: Python :: 3.12
Classifier: Programming Language :: Python :: 3.13
Classifier: Programming Language :: Python :: 3.14
Classifier: Operating System :: OS Independent
Classifier: Operating System :: Microsoft :: Windows
Classifier: Operating System :: POSIX :: Linux
Classifier: Operating System :: MacOS
Requires-Python: <4.0,>=3.10
License-File: LICENSE
Requires-Dist: click
Requires-Dist: ruamel-yaml
Requires-Dist: gitignore-parser
Requires-Dist: jsonschema
Provides-Extra: dev
Requires-Dist: pytest; extra == "dev"
Requires-Dist: pylint; extra == "dev"
Requires-Dist: pytest-cov; extra == "dev"
Requires-Dist: pytest-benchmark; extra == "dev"
Requires-Dist: poetry-plugin-export; extra == "dev"
Dynamic: license-file
